dizzer/__init__.py
dizzer/_codec.py
dizzer-0.1.2.dist-info/LICENSE
dizzer-0.1.2.dist-info/METADATA
dizzer-0.1.2.dist-info/WHEEL
dizzer-0.1.2.dist-info/top_level.txt
dizzer-0.1.2.dist-info/RECORD
